setup.py
bng_dist/Binomialdistribution.py
bng_dist/Gaussiandistribution.py
bng_dist/Generaldistribution.py
bng_dist/__init__.py
bng_dist.egg-info/PKG-INFO
bng_dist.egg-info/SOURCES.txt
bng_dist.egg-info/dependency_links.txt
bng_dist.egg-info/not-zip-safe
bng_dist.egg-info/top_level.txt