Metadata-Version: 1.0
Name: bng-dist
Version: 1.0
Summary: Gaussian and Binomial distributions
Home-page: UNKNOWN
Author: Hardik Trivedi
Author-email: htrivedicali@gmail.com
License: UNKNOWN
Platform: UNKNOWN
